album/__init__.py
album/package/__init__.py
album/package/argument_parsing.py
album/package/build_executable.py
album/package/install_all.py
album/package/install_mamba.py
album/package/solution_info.txt
album_package-0.5.0.dist-info/licenses/LICENSE
album_package-0.5.0.dist-info/METADATA
album_package-0.5.0.dist-info/WHEEL
album_package-0.5.0.dist-info/entry_points.txt
album_package-0.5.0.dist-info/top_level.txt
album_package-0.5.0.dist-info/RECORD
