Metadata-Version: 2.4
Name: album_package
Version: 0.5.0
Summary: album plugin to package solutions into executable install wizards
Home-page: https://gitlab.com/album-app/plugins/album-package
Author: Lucas Rieckert, Jan Philipp Albrecht, Deborah Schmidt
Maintainer: Lucas Rieckert, Jan Philipp Albrecht, Deborah Schmidt, Maximilian Otto
Maintainer-email: album@kyleharrington.com
License: MIT
Project-URL: Source, https://gitlab.com/album-app/plugins/album-package
Project-URL: Tracker, https://gitlab.com/album-app/plugins/album-package/issues
Keywords: virtual,environments,imaging,data analysis,packaging
Platform: any
Classifier: Development Status :: 3 - Alpha
Classifier: License :: OSI Approved :: MIT License
Classifier: Operating System :: MacOS :: MacOS X
Classifier: Operating System :: Microsoft :: Windows
Classifier: Operating System :: POSIX
Classifier: Programming Language :: Python :: 3.8
Classifier: Programming Language :: Python :: 3.9
Classifier: Programming Language :: Python :: Implementation :: PyPy
Classifier: Topic :: Utilities
Requires-Python: >=3.7
License-File: LICENSE
Requires-Dist: album<0.13,>=0.9.2
Requires-Dist: album-gui<0.6,>=0.5.0
Requires-Dist: pyinstaller>=4.8
Dynamic: license-file
